{"stats":{"minecraft:picked_up":{"minecraft:stripped_oak_log":2,"minecraft:crafting_table":2,"minecraft:allium":16,"minecraft:dark_oak_button":1,"minecraft:lilac":2,"minecraft:flint":3,"minecraft:oak_log":32,"minecraft:gunpowder":3,"minecraft:dirt":2230,"minecraft:raw_copper":83,"biomesoplenty:maple_planks":1,"minecraft:bone":2,"minecraft:apple":6,"minecraft:wheat_seeds":18,"minecraft:cobbled_deepslate":16,"minecraft:stone_pickaxe":3,"biomesoplenty:stripped_maple_log":4,"minecraft:light_gray_wool":5,"minecraft:chest":3,"travelersbackpack:blank_upgrade":2,"minecraft:oak_planks":2,"minecraft:spruce_trapdoor":1,"minecraft:raw_iron":8,"minecraft:stick":20,"minecraft:cooked_porkchop":3,"minecraft:torch":30,"minecraft:gravel":8,"minecraft:porkchop":3,"minecraft:diorite":33,"minecraft:spruce_door":1,"travelersbackpack:standard":1,"minecraft:arrow":4,"minecraft:rotten_flesh":4,"minecraft:granite":79,"minecraft:oak_sapling":77,"minecraft:mutton":1,"minecraft:coal":28,"minecraft:cobblestone":263},"minecraft:mined":{"minecraft:oak_sapling":1,"minecraft:crafting_table":2,"minecraft:torch":4,"minecraft:glow_lichen":2,"minecraft:granite":47,"minecraft:short_grass":45,"biomesoplenty:bush":67,"minecraft:allium":9,"minecraft:grass_block":682,"minecraft:chest":2,"minecraft:cobblestone":1,"minecraft:copper_ore":4,"minecraft:oak_planks":1,"minecraft:diorite":36,"minecraft:wall_torch":7,"minecraft:iron_ore":3,"minecraft:lilac":2,"minecraft:light_gray_wool":1,"biomesoplenty:hanging_cobweb":3,"minecraft:oak_log":33,"minecraft:coal_ore":2,"biomesoplenty:webbing":7,"minecraft:gravel":9,"minecraft:dirt":627,"minecraft:stone":236,"minecraft:deepslate":23,"minecraft:oak_leaves":164,"minecraft:fern":1},"minecraft:killed_by":{"minecraft:creeper":2,"minecraft:zombie":1},"minecraft:dropped":{"minecraft:gravel":1,"minecraft:wheat_seeds":16,"minecraft:lilac":1,"minecraft:cooked_porkchop":2,"minecraft:cobblestone":2,"minecraft:light_gray_wool":2,"minecraft:dark_oak_button":1,"minecraft:granite":33,"minecraft:spruce_door":1,"minecraft:flint":1,"minecraft:dirt":1210,"minecraft:spruce_trapdoor":1,"minecraft:chest":1,"minecraft:oak_sapling":37,"minecraft:stone_pickaxe":2,"biomesoplenty:maple_planks":1},"minecraft:broken":{"minecraft:stone_pickaxe":10,"minecraft:wooden_pickaxe":7},"minecraft:custom":{"minecraft:interact_with_furnace":6,"minecraft:mob_kills":6,"minecraft:interact_with_crafting_table":22,"minecraft:open_barrel":2,"minecraft:interact_with_stonecutter":1,"minecraft:time_since_death":37157,"minecraft:sleep_in_bed":5,"minecraft:climb_one_cm":1442,"minecraft:time_since_rest":21604,"minecraft:sprint_one_cm":294941,"minecraft:damage_taken":1831,"minecraft:walk_one_cm":551185,"minecraft:drop":651,"minecraft:damage_dealt":925,"minecraft:fly_one_cm":34912,"minecraft:open_chest":32,"minecraft:crouch_one_cm":1536,"minecraft:play_time":182798,"minecraft:deaths":5,"minecraft:sneak_time":335,"minecraft:jump":762,"minecraft:walk_on_water_one_cm":363,"minecraft:total_world_time":182798,"minecraft:fall_one_cm":26654,"minecraft:gravestones_collected":5,"minecraft:horse_one_cm":13710},"minecraft:used":{"minecraft:stone_pickaxe":1293,"minecraft:oak_planks":4,"minecraft:chest":4,"minecraft:wooden_pickaxe":449,"minecraft:rotten_flesh":1,"minecraft:torch":14,"minecraft:dirt":458,"minecraft:mutton":1,"minecraft:crafting_table":3,"minecraft:oak_log":9,"minecraft:apple":10,"minecraft:gravel":7,"minecraft:lilac":1,"minecraft:stone_bricks":1,"minecraft:light_gray_wool":2,"minecraft:beef":2,"minecraft:cooked_porkchop":3,"minecraft:egg":1},"minecraft:killed":{"minecraft:pig":1,"minecraft:sheep":1,"minecraft:skeleton":1,"minecraft:zombie":2},"minecraft:crafted":{"minecraft:oak_planks":88,"minecraft:cooked_porkchop":3,"minecraft:crafting_table":1,"minecraft:wooden_pickaxe":7,"biomesoplenty:maple_planks":16,"minecraft:oak_wood":3,"minecraft:bone_meal":2,"minecraft:dark_oak_button":1,"minecraft:stick":40,"minecraft:stone_pickaxe":20,"minecraft:chest":2,"minecraft:torch":12}},"DataVersion":3955}