{"stats":{"minecraft:used":{"minecraft:oak_fence":31,"minecraft:oak_trapdoor":3,"minecraft:stone_sword":68,"biomesoplenty:maple_boat":1,"minecraft:flint_and_steel":39,"minecraft:spruce_slab":38,"minecraft:stone_shovel":531,"minecraft:redstone":89,"minecraft:chest":9,"minecraft:spruce_planks":126,"minecraft:shield":37,"minecraft:iron_sword":421,"chisel:soft_bricks/cobblestone":1,"minecraft:cooked_salmon":1,"minecraft:stone_hoe":111,"minecraft:oak_door":2,"minecraft:torch":65,"minecraft:soul_sand":21,"minecraft:dirt":139,"minecraft:anvil":1,"minecraft:spruce_stairs":141,"minecraft:granite":6,"minecraft:snowball":200,"minecraft:oak_fence_gate":3,"minecraft:stone_brick_slab":13,"minecraft:oak_stairs":15,"minecraft:chicken_spawn_egg":128,"minecraft:iron_helmet":1,"minecraft:iron_boots":1,"minecraft:stone_bricks":5,"minecraft:stone_brick_stairs":31,"minecraft:bedrock":25,"minecraft:repeater":9,"minecraft:basalt":2,"minecraft:furnace":6,"minecraft:egg":115,"minecraft:cooked_beef":3,"minecraft:cobbled_deepslate":1,"minecraft:wheat_seeds":256,"minecraft:cooked_mutton":2,"minecraft:water_bucket":61,"minecraft:diorite":9,"minecraft:cobblestone_stairs":4,"minecraft:stone_pickaxe":920,"minecraft:cherry_planks":15,"minecraft:oak_planks":322,"minecraft:wooden_pickaxe":14,"minecraft:diamond_axe":44,"biomesoplenty:fir_boat":2,"minecraft:blue_bed":6,"minecraft:cobblestone_slab":2,"minecraft:oak_slab":2,"minecraft:crafting_table":13,"minecraft:tnt":627,"minecraft:campfire":34,"chisel:poison/stone":1,"chisel:solid_bricks/cobblestone":2,"minecraft:oak_log":534,"minecraft:lever":1,"minecraft:ender_eye":28,"minecraft:diamond_pickaxe":107,"minecraft:apple":21,"minecraft:firework_rocket":5,"minecraft:diamond_shovel":60,"travelersbackpack:netherite":3,"minecraft:bread":53,"minecraft:iron_pickaxe":103,"minecraft:suspicious_stew":1,"biomesoplenty:toadstool":1,"minecraft:lilac":4,"minecraft:stone_axe":1402,"minecraft:diamond_sword":39,"minecraft:cobblestone":373,"travelersbackpack:standard":5,"minecraft:white_banner":2,"minecraft:bucket":62,"minecraft:stripped_oak_log":19,"biomesoplenty:fir_log":13,"minecraft:bone_meal":12,"minecraft:diamond_leggings":1,"minecraft:experience_bottle":48},"minecraft:killed_by":{"minecraft:player":1,"minecraft:skeleton":1},"minecraft:custom":{"minecraft:interact_with_anvil":4,"minecraft:mob_kills":85,"minecraft:interact_with_crafting_table":92,"minecraft:open_barrel":23,"minecraft:interact_with_campfire":1,"minecraft:leave_game":10,"minecraft:time_since_death":93831,"minecraft:climb_one_cm":3916,"minecraft:sprint_one_cm":474111,"minecraft:walk_one_cm":3208907,"minecraft:damage_blocked_by_shield":1166,"minecraft:drop":68,"minecraft:talked_to_villager":13,"minecraft:play_time":677006,"minecraft:deaths":2,"minecraft:sneak_time":26746,"minecraft:walk_under_water_one_cm":16612,"minecraft:boat_one_cm":290850,"minecraft:jump":5817,"minecraft:interact_with_blast_furnace":1,"minecraft:walk_on_water_one_cm":35300,"minecraft:total_world_time":677006,"minecraft:gravestones_collected":2,"minecraft:interact_with_furnace":73,"minecraft:traded_with_villager":19,"minecraft:tune_noteblock":2,"minecraft:sleep_in_bed":8,"minecraft:time_since_rest":93937,"minecraft:damage_taken":3319,"minecraft:damage_dealt":16525,"minecraft:player_kills":3,"minecraft:fly_one_cm":1198703,"minecraft:swim_one_cm":8538,"minecraft:open_chest":184,"minecraft:crouch_one_cm":81268,"minecraft:fall_one_cm":123337},"minecraft:broken":{"minecraft:stone_pickaxe":8,"minecraft:stone_axe":10,"minecraft:iron_sword":1,"minecraft:iron_pickaxe":1,"minecraft:stone_shovel":4},"minecraft:picked_up":{"minecraft:charcoal":12,"minecraft:crafting_table":6,"minecraft:wheat":123,"minecraft:ominous_bottle":1,"minecraft:chicken":1,"minecraft:diamond_sword":2,"minecraft:wooden_pickaxe":1,"minecraft:oak_stairs":1,"minecraft:enchanted_book":1,"minecraft:stone_brick_stairs":3,"chisel:panel/cobblestone":1,"minecraft:raw_copper":52,"minecraft:string":4,"minecraft:oak_trapdoor":1,"minecraft:moss_carpet":2,"minecraft:cooked_salmon":1,"minecraft:cyan_carpet":4,"minecraft:cracked_stone_bricks":1,"minecraft:cobbled_deepslate":30,"minecraft:eye_armor_trim_smithing_template":1,"minecraft:beef":7,"minecraft:rose_bush":1,"minecraft:redstone_torch":1,"minecraft:ender_eye":11,"minecraft:spruce_slab":4,"minecraft:sugar_cane":14,"minecraft:chest":1,"minecraft:egg":39,"minecraft:raw_iron":53,"minecraft:stick":194,"chisel:soft_bricks/cobblestone":1,"travelersbackpack:netherite":1,"minecraft:oak_fence":2,"minecraft:torch":20,"minecraft:bowl":1,"minecraft:spruce_stairs":3,"minecraft:cherry_log":2,"minecraft:diorite":14,"minecraft:tnt":468,"minecraft:arrow":30,"minecraft:rotten_flesh":28,"minecraft:hay_block":7,"minecraft:mutton":1,"minecraft:white_wool":4,"minecraft:cobblestone":1046,"minecraft:stripped_oak_log":26,"minecraft:lilac":34,"minecraft:feather":2,"minecraft:basalt":2,"minecraft:cherry_planks":79,"minecraft:iron_door":2,"minecraft:water_bucket":1,"minecraft:andesite":10,"minecraft:leather":2,"minecraft:brown_wool":1,"biomesoplenty:fir_sapling":34,"biomesoplenty:fir_log":287,"minecraft:magenta_dye":1,"minecraft:oak_log":712,"minecraft:dirt":694,"minecraft:blue_bed":6,"minecraft:white_banner":2,"minecraft:cooked_mutton":3,"travelersbackpack:tanks_upgrade":1,"minecraft:bone":29,"minecraft:apple":22,"minecraft:stone_bricks":3,"minecraft:kelp":1,"minecraft:bow":1,"minecraft:wheat_seeds":414,"biomesoplenty:fir_boat":4,"biomesoplenty:maple_log":6,"minecraft:oak_planks":10,"travelersbackpack:blank_upgrade":2,"minecraft:soul_sand":1,"biomesoplenty:toadstool":4,"minecraft:stone_brick_slab":1,"minecraft:spruce_sapling":22,"minecraft:spruce_log":198,"minecraft:spider_eye":1,"travelersbackpack:standard":4,"chisel:chisel":1,"biomesoplenty:yellow_maple_sapling":2,"chisel:solid_bricks/cobblestone":2,"minecraft:granite":16,"minecraft:oak_sapling":233,"minecraft:coal":253,"minecraft:diamond_pickaxe":1},"minecraft:dropped":{"minecraft:enchanted_book":1,"minecraft:iron_ingot":1,"minecraft:water_bucket":1,"minecraft:wheat_seeds":3,"minecraft:oak_log":2,"biomesoplenty:fir_boat":4,"chisel:chisel":1,"minecraft:chicken_spawn_egg":128,"minecraft:coal":9,"biomesoplenty:fir_sapling":3,"minecraft:dirt":15,"minecraft:torch":28,"minecraft:cherry_planks":59,"minecraft:potion":1,"minecraft:string":4,"minecraft:white_wool":1,"biomesoplenty:toadstool":2,"minecraft:cobbled_deepslate":21,"minecraft:bowl":1,"minecraft:experience_bottle":72,"biomesoplenty:yellow_maple_sapling":2,"minecraft:chicken":1,"minecraft:ender_eye":1,"minecraft:cooked_mutton":1,"minecraft:eye_armor_trim_smithing_template":1,"minecraft:magenta_dye":1,"minecraft:wooden_pickaxe":1},"minecraft:crafted":{"minecraft:oak_door":3,"minecraft:oak_planks":692,"minecraft:cobblestone_slab":6,"minecraft:stone_shovel":4,"travelersbackpack:crafting_upgrade":1,"biomesoplenty:maple_planks":24,"minecraft:furnace":6,"minecraft:stone":390,"minecraft:cobblestone_stairs":4,"minecraft:bone_meal":12,"biomesoplenty:maple_boat":1,"minecraft:oak_trapdoor":2,"minecraft:stone_brick_slab":24,"minecraft:spruce_stairs":172,"minecraft:iron_boots":1,"minecraft:spruce_slab":36,"minecraft:stone_pickaxe":9,"minecraft:chest":59,"minecraft:stone_hoe":1,"minecraft:oak_fence":78,"minecraft:wheat":7,"minecraft:cooked_beef":3,"chisel:chisel":1,"minecraft:oak_slab":6,"biomesoplenty:fir_boat":3,"minecraft:emerald":19,"minecraft:crafting_table":10,"minecraft:spruce_planks":764,"minecraft:wooden_pickaxe":1,"minecraft:iron_helmet":1,"minecraft:iron_sword":2,"minecraft:bucket":2,"minecraft:campfire":47,"minecraft:stone_axe":11,"minecraft:air":84,"minecraft:bread":64,"biomesoplenty:fir_planks":516,"minecraft:oak_fence_gate":6,"minecraft:stone_brick_stairs":32,"minecraft:spruce_trapdoor":32,"minecraft:iron_chestplate":1,"minecraft:shield":1,"minecraft:stick":820,"minecraft:iron_ingot":53,"minecraft:iron_pickaxe":1,"minecraft:oak_stairs":16,"minecraft:stone_sword":1,"minecraft:iron_leggings":1,"minecraft:torch":96,"minecraft:shears":1},"minecraft:killed":{"minecraft:cave_spider":1,"minecraft:spider":2,"minecraft:skeleton":24,"minecraft:chicken":12,"minecraft:drowned":1,"minecraft:husk":18,"minecraft:frog":7,"minecraft:sheep":1,"minecraft:zombie":14,"minecraft:player":3,"minecraft:enderman":1,"minecraft:cow":3},"minecraft:mined":{"minecraft:red_nether_bricks":1,"chisel:solid_bricks/cobblestone":2,"biomesoplenty:red_maple_leaves":1,"minecraft:granite":15,"biomesoplenty:bush":220,"minecraft:grass_block":500,"chisel:soft_bricks/cobblestone":1,"biomesoplenty:yellow_maple_leaf_pile":1,"minecraft:spawner":4,"minecraft:large_fern":1,"minecraft:hay_block":7,"minecraft:oak_trapdoor":1,"minecraft:dark_oak_trapdoor":1,"biomesoplenty:toadstool":1,"minecraft:iron_ore":15,"minecraft:fire":23,"minecraft:cobbled_deepslate":4,"minecraft:andesite":10,"biomesoplenty:hanging_cobweb":3,"minecraft:dirt_path":1,"minecraft:oak_stairs":1,"biomesoplenty:webbing":14,"minecraft:crimson_door":2,"minecraft:stripped_oak_log":27,"minecraft:stone":1012,"minecraft:spruce_slab":2,"biomesoplenty:maple_log":2,"minecraft:cherry_planks":36,"minecraft:basalt":2,"minecraft:stone_brick_slab":1,"travelersbackpack:standard":1,"biomesoplenty:hanging_cobweb_strand":2,"minecraft:oak_fence":2,"minecraft:crafting_table":6,"minecraft:torch":6,"minecraft:short_grass":507,"minecraft:chest":1,"minecraft:campfire":10,"minecraft:tall_grass":52,"minecraft:copper_ore":1,"minecraft:cobblestone":19,"minecraft:sugar_cane":1,"minecraft:oak_planks":10,"minecraft:wall_torch":7,"minecraft:diorite":14,"minecraft:iron_door":2,"minecraft:blue_bed":6,"minecraft:spruce_stairs":5,"minecraft:redstone_torch":1,"minecraft:wheat":143,"minecraft:lilac":28,"minecraft:spruce_log":185,"minecraft:tnt":495,"biomesoplenty:fir_log":303,"minecraft:white_wall_banner":1,"minecraft:stone_brick_stairs":4,"minecraft:coal_ore":15,"minecraft:oak_log":599,"chisel:panel/cobblestone":1,"biomesoplenty:fir_leaves":7,"minecraft:cyan_carpet":6,"minecraft:dirt":135,"minecraft:cobweb":2,"minecraft:cracked_stone_bricks":1,"minecraft:stone_bricks":3,"minecraft:oak_leaves":157,"minecraft:deepslate":5,"minecraft:fern":30}},"DataVersion":3955}