{
  "deeperdarker:recipes/transportation/echo_boat": {
    "criteria": {
      "in_water": "2025-04-17 02:48:46 +0000"
    },
    "done": true
  },
  "biomesoplenty:recipes/transportation/willow_boat": {
    "criteria": {
      "in_water": "2025-04-17 02:48:46 +0000"
    },
    "done": true
  },
  "the_bumblezone:structures/enter_all_structures": {
    "criteria": {
      "in_goliath_honey_fountain": "2025-04-17 02:41:12 +0000",
      "in_mite_fortress": "2025-04-17 02:41:12 +0000"
    },
    "done": false
  },
  "deeperdarker:recipes/transportation/bloom_boat": {
    "criteria": {
      "in_water": "2025-04-17 02:48:46 +0000"
    },
    "done": true
  },
  "minecraft:recipes/decorations/crafting_table": {
    "criteria": {
      "unlock_right_away": "2025-04-17 02:41:11 +0000"
    },
    "done": true
  },
  "minecraft:recipes/decorations/chest": {
    "criteria": {
      "has_lots_of_items": "2025-04-17 02:51:12 +0000"
    },
    "done": true
  },
  "minecraft:adventure/sleep_in_bed": {
    "criteria": {
      "slept_in_bed": "2025-04-17 02:46:52 +0000"
    },
    "done": true
  },
  "minecraft:recipes/transportation/cherry_boat": {
    "criteria": {
      "in_water": "2025-04-17 02:48:46 +0000"
    },
    "done": true
  },
  "biomesoplenty:recipes/transportation/umbran_boat": {
    "criteria": {
      "in_water": "2025-04-17 02:48:46 +0000"
    },
    "done": true
  },
  "minecraft:recipes/redstone/tripwire_hook": {
    "criteria": {
      "has_string": "2025-04-17 02:49:07 +0000"
    },
    "done": true
  },
  "minecraft:recipes/transportation/bamboo_raft": {
    "criteria": {
      "in_water": "2025-04-17 02:48:46 +0000"
    },
    "done": true
  },
  "minecraft:recipes/decorations/candle": {
    "criteria": {
      "has_string": "2025-04-17 02:49:07 +0000"
    },
    "done": true
  },
  "minecraft:recipes/food/bread": {
    "criteria": {
      "has_wheat": "2025-04-17 02:48:43 +0000"
    },
    "done": true
  },
  "biomesoplenty:recipes/transportation/dead_boat": {
    "criteria": {
      "in_water": "2025-04-17 02:48:46 +0000"
    },
    "done": true
  },
  "biomesoplenty:recipes/transportation/magic_boat": {
    "criteria": {
      "in_water": "2025-04-17 02:48:46 +0000"
    },
    "done": true
  },
  "minecraft:recipes/building_blocks/hay_block": {
    "criteria": {
      "has_wheat": "2025-04-17 02:48:43 +0000"
    },
    "done": true
  },
  "incendium:technical/new_player": {
    "criteria": {
      "requirement": "2025-04-17 02:41:11 +0000"
    },
    "done": true
  },
  "betternether:root": {
    "criteria": {
      "welcome": "2025-04-17 02:41:12 +0000"
    },
    "done": true
  },
  "better_babies:pack": {
    "criteria": {
      "trigger": "2025-04-17 02:41:11 +0000"
    },
    "done": true
  },
  "travelersbackpack:recipes/misc/skeleton": {
    "criteria": {
      "has_arrow": "2025-04-17 02:49:24 +0000"
    },
    "done": true
  },
  "minecraft:recipes/misc/charcoal": {
    "criteria": {
      "has_log": "2025-04-17 02:49:59 +0000"
    },
    "done": true
  },
  "the_bumblezone:root": {
    "criteria": {
      "instant_granted": "2025-04-17 02:41:11 +0000"
    },
    "done": true
  },
  "biomesoplenty:biomesoplenty/root": {
    "criteria": {
      "coniferous_forest": "2025-04-17 02:41:12 +0000"
    },
    "done": true
  },
  "biomesoplenty:recipes/transportation/pine_boat": {
    "criteria": {
      "in_water": "2025-04-17 02:48:46 +0000"
    },
    "done": true
  },
  "minecraft:recipes/transportation/acacia_boat": {
    "criteria": {
      "in_water": "2025-04-17 02:48:46 +0000"
    },
    "done": true
  },
  "minecraft:recipes/building_blocks/oak_planks": {
    "criteria": {
      "has_logs": "2025-04-17 02:49:59 +0000"
    },
    "done": true
  },
  "minecraft:recipes/combat/crossbow": {
    "criteria": {
      "has_string": "2025-04-17 02:49:07 +0000"
    },
    "done": true
  },
  "betterdungeons:root": {
    "criteria": {
      "always": "2025-04-17 02:41:11 +0000"
    },
    "done": true
  },
  "incendium:technical/using/shield": {
    "criteria": {
      "log_spam_fixer": "2025-04-17 02:41:12 +0000"
    },
    "done": false
  },
  "travelersbackpack:recipes/misc/cake": {
    "criteria": {
      "has_egg": "2025-04-17 02:51:12 +0000"
    },
    "done": true
  },
  "minecraft:recipes/building_blocks/oak_wood": {
    "criteria": {
      "has_log": "2025-04-17 02:49:59 +0000"
    },
    "done": true
  },
  "minecraft:recipes/transportation/jungle_boat": {
    "criteria": {
      "in_water": "2025-04-17 02:48:46 +0000"
    },
    "done": true
  },
  "travelersbackpack:recipes/misc/hay": {
    "criteria": {
      "has_wheat": "2025-04-17 02:48:43 +0000"
    },
    "done": true
  },
  "minecraft:recipes/food/cake": {
    "criteria": {
      "has_egg": "2025-04-17 02:51:12 +0000"
    },
    "done": true
  },
  "minecraft:recipes/combat/bow": {
    "criteria": {
      "has_string": "2025-04-17 02:49:07 +0000"
    },
    "done": true
  },
  "minecraft:recipes/tools/fishing_rod": {
    "criteria": {
      "has_string": "2025-04-17 02:49:07 +0000"
    },
    "done": true
  },
  "biomesoplenty:recipes/transportation/fir_boat": {
    "criteria": {
      "in_water": "2025-04-17 02:48:46 +0000"
    },
    "done": true
  },
  "biomesoplenty:biomesoplenty/all_biomes": {
    "criteria": {
      "shrubland": "2025-04-17 02:41:44 +0000",
      "rocky_shrubland": "2025-04-17 02:42:01 +0000",
      "coniferous_forest": "2025-04-17 02:41:12 +0000"
    },
    "done": false
  },
  "travelersbackpack:recipes/misc/spider": {
    "criteria": {
      "has_string": "2025-04-17 02:49:07 +0000"
    },
    "done": true
  },
  "biomesoplenty:recipes/transportation/maple_boat": {
    "criteria": {
      "in_water": "2025-04-17 02:48:46 +0000"
    },
    "done": true
  },
  "minecraft:recipes/transportation/spruce_boat": {
    "criteria": {
      "in_water": "2025-04-17 02:48:46 +0000"
    },
    "done": true
  },
  "minecraft:husbandry/root": {
    "criteria": {
      "consumed_item": "2025-04-17 02:51:02 +0000"
    },
    "done": true
  },
  "minecraft:recipes/transportation/birch_boat": {
    "criteria": {
      "in_water": "2025-04-17 02:48:46 +0000"
    },
    "done": true
  },
  "betterdeserttemples:root": {
    "criteria": {
      "always": "2025-04-17 02:41:11 +0000"
    },
    "done": true
  },
  "minecraft:recipes/transportation/oak_boat": {
    "criteria": {
      "in_water": "2025-04-17 02:48:46 +0000"
    },
    "done": true
  },
  "biomesoplenty:recipes/transportation/redwood_boat": {
    "criteria": {
      "in_water": "2025-04-17 02:48:46 +0000"
    },
    "done": true
  },
  "minecraft:recipes/transportation/mangrove_boat": {
    "criteria": {
      "in_water": "2025-04-17 02:48:46 +0000"
    },
    "done": true
  },
  "incendium:technical/scroll_of_returning": {
    "criteria": {
      "log_spam_fixer": "2025-04-17 02:41:12 +0000"
    },
    "done": false
  },
  "biomesoplenty:recipes/transportation/hellbark_boat": {
    "criteria": {
      "in_water": "2025-04-17 02:48:46 +0000"
    },
    "done": true
  },
  "incendium:technical/using/ragnarok": {
    "criteria": {
      "log_spam_fixer": "2025-04-17 02:41:12 +0000"
    },
    "done": false
  },
  "biomesoplenty:recipes/transportation/jacaranda_boat": {
    "criteria": {
      "in_water": "2025-04-17 02:48:46 +0000"
    },
    "done": true
  },
  "biomesoplenty:recipes/transportation/mahogany_boat": {
    "criteria": {
      "in_water": "2025-04-17 02:48:46 +0000"
    },
    "done": true
  },
  "biomesoplenty:recipes/transportation/palm_boat": {
    "criteria": {
      "in_water": "2025-04-17 02:48:46 +0000"
    },
    "done": true
  },
  "biomesoplenty:recipes/transportation/empyreal_boat": {
    "criteria": {
      "in_water": "2025-04-17 02:48:46 +0000"
    },
    "done": true
  },
  "the_bumblezone:wiki": {
    "criteria": {
      "instant_granted": "2025-04-17 02:41:11 +0000"
    },
    "done": true
  },
  "incendium:technical/using/trailblazer": {
    "criteria": {
      "log_spam_fixer": "2025-04-17 02:41:12 +0000"
    },
    "done": false
  },
  "minecraft:recipes/building_blocks/white_wool_from_string": {
    "criteria": {
      "has_string": "2025-04-17 02:49:07 +0000"
    },
    "done": true
  },
  "minecraft:husbandry/balanced_diet": {
    "criteria": {
      "bread": "2025-04-17 02:51:02 +0000"
    },
    "done": false
  },
  "minecraft:recipes/decorations/loom": {
    "criteria": {
      "has_string": "2025-04-17 02:49:07 +0000"
    },
    "done": true
  },
  "minecraft:story/root": {
    "criteria": {
      "crafting_table": "2025-04-17 02:50:05 +0000"
    },
    "done": true
  },
  "minecraft:recipes/transportation/dark_oak_boat": {
    "criteria": {
      "in_water": "2025-04-17 02:48:46 +0000"
    },
    "done": true
  },
  "DataVersion": 3955
}